code/__init__.py
code/tools.py
network_inference_mike-0.0.2.dist-info/LICENSE
network_inference_mike-0.0.2.dist-info/METADATA
network_inference_mike-0.0.2.dist-info/WHEEL
network_inference_mike-0.0.2.dist-info/top_level.txt
network_inference_mike-0.0.2.dist-info/RECORD
