Metadata-Version: 2.1
Name: network-inference-mike
Version: 0.0.2
Summary: Tools for gene regulatory network inference.
Home-page: https://github.com/mikesaint-antoine/network_inference
Author: Mike Saint-Antoine
Author-email: mikest@udel.com
License: UNKNOWN
Platform: UNKNOWN
Classifier: Programming Language :: Python :: 3
Classifier: License :: OSI Approved :: MIT License
Classifier: Operating System :: OS Independent
License-File: LICENSE
